webshell/__init__.py
webshell/admin.py
webshell/forms.py
webshell/models.py
webshell/tests.py
webshell/urls.py
webshell/views.py
webshell/migrations/0001_initial.py
webshell/migrations/__init__.py
webshell/static/css/codemirror.css
webshell/static/css/highlight.min.css
webshell/static/js/codemirror.js
webshell/static/js/highlight.min.js
webshell/static/js/python.js
webshell/templates/webshell/change_form.html
django_webshell-0.4.0.dist-info/LICENSE
django_webshell-0.4.0.dist-info/METADATA
django_webshell-0.4.0.dist-info/WHEEL
django_webshell-0.4.0.dist-info/top_level.txt
django_webshell-0.4.0.dist-info/RECORD
