Metadata-Version: 2.1
Name: django-webshell
Version: 0.4.0
Summary: Django application for running python code in your project's environment from django admin.
Home-page: http://github.com/onrik/django-webshell
Author: Andrey
Author-email: and@rey.im
License: MIT
Download-URL: http://github.com/onrik/django-webshell/tarball/master
Platform: UNKNOWN
Classifier: Development Status :: 5 - Production/Stable
Classifier: Environment :: Web Environment
Classifier: Framework :: Django
Classifier: Intended Audience :: Developers
Classifier: License :: OSI Approved :: MIT License
Classifier: Operating System :: OS Independent
Classifier: Programming Language :: Python
Classifier: Programming Language :: Python :: 2
Classifier: Programming Language :: Python :: 3
Classifier: Topic :: Software Development :: Libraries :: Python Modules
License-File: LICENSE
